LICENSE
MANIFEST.in
README.rst
setup.py
tpkbdctl/__init__.py
tpkbdctl/cmd.py
tpkbdctl.egg-info/PKG-INFO
tpkbdctl.egg-info/SOURCES.txt
tpkbdctl.egg-info/dependency_links.txt
tpkbdctl.egg-info/entry_points.txt
tpkbdctl.egg-info/not-zip-safe
tpkbdctl.egg-info/top_level.txt