Metadata-Version: 1.0
Name: tpkbdctl
Version: 0.2.2
Summary: Thinkpad Keyboard Control Tool
Home-page: http://github.com/bseibold/tpkbdctl
Author: Bernhard Seibold
Author-email: bernhard.seibold@gmail.com
License: GPLv2
Platform: UNKNOWN
